myz/__init__.py
tests/__init__.py
MYZ-0.2.0.dist-info/AUTHORS
MYZ-0.2.0.dist-info/LICENSE
MYZ-0.2.0.dist-info/METADATA
MYZ-0.2.0.dist-info/WHEEL
MYZ-0.2.0.dist-info/top_level.txt
MYZ-0.2.0.dist-info/RECORD
